{"Version":"1.0.0.0","LastState":11,"Modules":[{"IsEncoderOffsetConfigured":true,"IsDeviceSelectionCompleted":true,"IsConfigurationCompleted":true,"ModuleName":"Front Left","ModuleId":0,"Encoder":{"Id":1,"Name":"LeftFront","Model":"CANCoder","CANbus":"30C395F03353385320202034100E03FF","CANbusFriendly":"CTRE Chain"},"SteerMotor":{"Id":4,"Name":"LeftFrontSteer","Model":"Talon FX","CANbus":"30C395F03353385320202034100E03FF","CANbusFriendly":"CTRE Chain"},"DriveMotor":{"Id":1,"Name":"LeftFrontDrive","Model":"Talon FX vers. C","CANbus":"30C395F03353385320202034100E03FF","CANbusFriendly":"CTRE Chain"},"EncoderOffset":-0.288330078125,"DriveMotorSelectionState":1,"SteerMotorSelectionState":1,"SteerEncoderSelectionState":1},{"IsEncoderOffsetConfigured":true,"IsDeviceSelectionCompleted":true,"IsConfigurationCompleted":true,"ModuleName":"Front Right","ModuleId":1,"Encoder":{"Id":3,"Name":"RightFront","Model":"CANCoder","CANbus":"30C395F03353385320202034100E03FF","CANbusFriendly":"CTRE Chain"},"SteerMotor":{"Id":5,"Name":"RightFrontSteer","Model":"Talon FX","CANbus":"30C395F03353385320202034100E03FF","CANbusFriendly":"CTRE Chain"},"DriveMotor":{"Id":7,"Name":"RightFrontDrive","Model":"Talon FX vers. C","CANbus":"30C395F03353385320202034100E03FF","CANbusFriendly":"CTRE Chain"},"EncoderOffset":-0.4951171875,"DriveMotorSelectionState":1,"SteerMotorSelectionState":1,"SteerEncoderSelectionState":1},{"IsEncoderOffsetConfigured":true,"IsDeviceSelectionCompleted":true,"IsConfigurationCompleted":true,"ModuleName":"Back Left","ModuleId":2,"Encoder":{"Id":2,"Name":"LeftRear","Model":"CANCoder","CANbus":"30C395F03353385320202034100E03FF","CANbusFriendly":"CTRE Chain"},"SteerMotor":{"Id":0,"Name":"LeftRearSteer","Model":"Talon FX","CANbus":"30C395F03353385320202034100E03FF","CANbusFriendly":"CTRE Chain"},"DriveMotor":{"Id":3,"Name":"LeftRearDrive","Model":"Talon FX vers. C","CANbus":"30C395F03353385320202034100E03FF","CANbusFriendly":"CTRE Chain"},"EncoderOffset":-0.353271484375,"DriveMotorSelectionState":1,"SteerMotorSelectionState":1,"SteerEncoderSelectionState":1},{"IsEncoderOffsetConfigured":true,"IsDeviceSelectionCompleted":true,"IsConfigurationCompleted":true,"ModuleName":"Back Right","ModuleId":3,"Encoder":{"Id":0,"Name":"RightRear","Model":"CANCoder","CANbus":"30C395F03353385320202034100E03FF","CANbusFriendly":"CTRE Chain"},"SteerMotor":{"Id":6,"Name":"RightRearSteer","Model":"Talon FX","CANbus":"30C395F03353385320202034100E03FF","CANbusFriendly":"CTRE Chain"},"DriveMotor":{"Id":2,"Name":"RightRearDrive","Model":"Talon FX vers. C","CANbus":"30C395F03353385320202034100E03FF","CANbusFriendly":"CTRE Chain"},"EncoderOffset":0.466552734375,"DriveMotorSelectionState":1,"SteerMotorSelectionState":1,"SteerEncoderSelectionState":1}],"SwerveOptions":{"IsValidConfiguration":true,"Gyro":{"Id":0,"Name":"Pigeon 2 (Device ID 0)","Model":"Pigeon 2","CANbus":"30C395F03353385320202034100E03FF","CANbusFriendly":"CTRE Chain"},"VerticalTrackSizeInches":22.0,"HorizontalTrackSizeInches":22.0,"WheelRadiusInches":2.0,"IsLeftSideInverted":false,"IsRightSideInverted":true,"SwerveModuleType":4,"SwerveModuleConfiguration":{"_CouplingRatio":3.5714285714285716,"_CustomName":"L3","SteerRatio":21.428571428571427,"Flipped":4,"DriveRatio":6.122448979591837,"CouplingRatio":3.5714285714285716,"CustomName":"L3"},"HasVerifiedSteer":true,"HasVerifiedDrive":true,"IsSteerMotorReversed":true}}